eof_fixer/__init__.py
eof_fixer/main.py
eof_fixer/py.typed
eof_fixer-0.3.0.dist-info/WHEEL
eof_fixer-0.3.0.dist-info/entry_points.txt
eof_fixer-0.3.0.dist-info/METADATA
eof_fixer-0.3.0.dist-info/RECORD
