Metadata-Version: 2.3
Name: eof-fixer
Version: 0.3.0
Summary: A command-line tool that ensures all your text files end with exactly one newline character
Keywords: python
Author: modern-python
Classifier: Typing :: Typed
Classifier: Programming Language :: Python :: 3.10
Classifier: Programming Language :: Python :: 3.11
Classifier: Programming Language :: Python :: 3.12
Classifier: Programming Language :: Python :: 3.13
Classifier: Programming Language :: Python :: 3.14
Requires-Dist: pathspec
Requires-Python: >=3.10, <4
Project-URL: Changelogs, https://github.com/modern-python/eof-fixer/releases
Project-URL: Issues, https://github.com/modern-python/eof-fixer/issues
Project-URL: Repository, https://github.com/modern-python/eof-fixer
